sdkms/__init__.py
sdkms/v1/__init__.py
sdkms/v1/api_client.py
sdkms/v1/configuration.py
sdkms/v1/rest.py
sdkms/v1/apis/__init__.py
sdkms/v1/apis/accounts_api.py
sdkms/v1/apis/approval_requests_api.py
sdkms/v1/apis/apps_api.py
sdkms/v1/apis/authentication_api.py
sdkms/v1/apis/aws_api.py
sdkms/v1/apis/child_account_users_api.py
sdkms/v1/apis/child_accounts_api.py
sdkms/v1/apis/digest_api.py
sdkms/v1/apis/encryption_and_decryption_api.py
sdkms/v1/apis/groups_api.py
sdkms/v1/apis/logs_api.py
sdkms/v1/apis/plugins_api.py
sdkms/v1/apis/security_objects_api.py
sdkms/v1/apis/sign_and_verify_api.py
sdkms/v1/apis/stats_api.py
sdkms/v1/apis/two_factor_authentication_api.py
sdkms/v1/apis/users_api.py
sdkms/v1/apis/wrapping_and_unwrapping_api.py
sdkms/v1/models/__init__.py
sdkms/v1/models/account.py
sdkms/v1/models/account_request.py
sdkms/v1/models/account_state.py
sdkms/v1/models/ad_decrypt_input.py
sdkms/v1/models/ad_encrypt_input.py
sdkms/v1/models/agree_key_mechanism.py
sdkms/v1/models/agree_key_request.py
sdkms/v1/models/app.py
sdkms/v1/models/app_auth_type.py
sdkms/v1/models/app_credential.py
sdkms/v1/models/app_credential_response.py
sdkms/v1/models/app_credential_signedjwt.py
sdkms/v1/models/app_credential_signedjwt_signing_keys.py
sdkms/v1/models/app_credential_trustedca.py
sdkms/v1/models/app_oauth_config.py
sdkms/v1/models/app_permissions.py
sdkms/v1/models/app_request.py
sdkms/v1/models/app_reset_secret_request.py
sdkms/v1/models/approvable_result.py
sdkms/v1/models/approval_request.py
sdkms/v1/models/approval_request_request.py
sdkms/v1/models/approval_status.py
sdkms/v1/models/approval_subject.py
sdkms/v1/models/approve_request.py
sdkms/v1/models/audit_log_response.py
sdkms/v1/models/auth_config.py
sdkms/v1/models/auth_config_password.py
sdkms/v1/models/auth_config_signed_jwt.py
sdkms/v1/models/auth_response.py
sdkms/v1/models/auth_type.py
sdkms/v1/models/azure_key_vault_response.py
sdkms/v1/models/azure_key_vault_type.py
sdkms/v1/models/base64_url_safe.py
sdkms-5.4.2891.dist-info/LICENSE
sdkms-5.4.2891.dist-info/METADATA
sdkms-5.4.2891.dist-info/WHEEL
sdkms-5.4.2891.dist-info/top_level.txt
sdkms-5.4.2891.dist-info/RECORD
