Metadata-Version: 2.1
Name: sdkms
Version: 5.4.2891
Summary: Fortanix SDKMS REST API
Home-page: https://support.fortanix.com
Author: Fortanix
Author-email: support@fortanix.com
License: Apache 2.0
Keywords: Swagger,Fortanix SDKMS REST API
Classifier: Development Status :: 5 - Production/Stable
Classifier: Intended Audience :: Developers
Classifier: Intended Audience :: System Administrators
Classifier: License :: OSI Approved :: Apache Software License
Classifier: Programming Language :: Python :: 2
Classifier: Programming Language :: Python :: 3
Classifier: Topic :: Security :: Cryptography
License-File: LICENSE
Requires-Dist: certifi
Requires-Dist: python-dateutil
Requires-Dist: six >=1.10
Requires-Dist: urllib3 >=1.15
